{
  "categories": [
    {
      "id": 2,
      "codigo": "A002",
      "nombre": "Tela Poliéster",
      "almacen": "Almacén Norte",
      "categoria": "Poliéster",
      "cantidad": 80
    },
    {
      "id": 3,
      "codigo": "A003",
      "nombre": "Tela Lino",
      "almacen": "Almacén Sur",
      "categoria": "Lino",
      "cantidad": 50
    },
    {
      "id": 4,
      "codigo": "A004",
      "nombre": "Tela Seda",
      "almacen": "Almacén Este",
      "categoria": "Seda",
      "cantidad": 30
    }
  ],
  "storerooms": [
    {
      "id": 1,
      "nombre": "Almacén A",
      "temperatura": {
        "actual": "21",
        "maxima": 28,
        "minima": 18,
        "unidad": "Celsius"
      },
      "humedad": {
        "actual": "77",
        "maxima": 60,
        "minima": 30,
        "unidad": "%"
      }
    },
    {
      "id": 2,
      "nombre": "Almacén B",
      "temperatura": {
        "actual": 28,
        "maxima": 26.5,
        "minima": 19.5,
        "unidad": "Celsius"
      },
      "humedad": {
        "actual": 15,
        "maxima": 65,
        "minima": 35,
        "unidad": "%"
      }
    },
    {
      "id": 3,
      "nombre": "Almacén C",
      "temperatura": {
        "actual": "52",
        "maxima": 25,
        "minima": 17,
        "unidad": "Celsius"
      },
      "humedad": {
        "actual": "51",
        "maxima": 70,
        "minima": 40,
        "unidad": "%"
      }
    }
  ],
  "thermometers": [
    {
      "id": 1,
      "name": "Thermometer Pro",
      "model": "TP-100",
      "storeroom": 1
    },
    {
      "id": 2,
      "name": "Thermometer A+",
      "model": "DT-101",
      "storeroom": 2
    },
    {
      "id": 3,
      "name": "Digital Thermometer",
      "model": "DT-102",
      "storeroom": 3
    }
  ],
  "hygrometers": [
    {
      "id": 1,
      "name": "Hygrometer Max",
      "model": "HM-200",
      "storeroom": 1
    },
    {
      "id": 2,
      "name": "Hygrometer A+",
      "model": "HR-201",
      "storeroom": 2
    },
    {
      "id": 3,
      "name": "Smart Hygrometer",
      "model": "SH-202",
      "storeroom": 3
    }
  ],
  "heaters": [
    {
      "id": 1,
      "name": "Heater Pro",
      "model": "HP-300",
      "storeroom": 1,
      "temperature": "41"
    },
    {
      "id": 2,
      "name": "Heater A+",
      "model": "HP-150",
      "storeroom": 2,
      "temperature": 28
    },
    {
      "id": 3,
      "name": "Smart Heater",
      "model": "HP-200",
      "storeroom": 3,
      "temperature": "52"
    }
  ],
  "humidifiers": [
    {
      "id": 1,
      "name": "Humidifier Pro",
      "model": "HP-400",
      "storeroom": 1,
      "humidity": "77"
    },
    {
      "id": 2,
      "name": "Smart Humidifier",
      "model": "SH-250",
      "storeroom": 2,
      "humidity": 15
    },
    {
      "id": 3,
      "name": "Humidifier B+",
      "model": "SH-300",
      "storeroom": 3,
      "humidity": 11
    }
  ]
}